[
  {
    "year": 1995,
    "avg_rating": 3.75,
    "n_ratings": 4
  },
  {
    "year": 1996,
    "avg_rating": 3.554376613430552,
    "n_ratings": 1732721
  },
  {
    "year": 1997,
    "avg_rating": 3.592635274674475,
    "n_ratings": 763613
  },
  {
    "year": 1998,
    "avg_rating": 3.5234701094958094,
    "n_ratings": 329419
  },
  {
    "year": 1999,
    "avg_rating": 3.6177437225594415,
    "n_ratings": 1230159
  },
  {
    "year": 2000,
    "avg_rating": 3.5783923066395307,
    "n_ratings": 2031258
  },
  {
    "year": 2001,
    "avg_rating": 3.5363069098006523,
    "n_ratings": 1237836
  },
  {
    "year": 2002,
    "avg_rating": 3.4851987489700345,
    "n_ratings": 909011
  },
  {
    "year": 2003,
    "avg_rating": 3.471799415067353,
    "n_ratings": 1077389
  },
  {
    "year": 2004,
    "avg_rating": 3.427290118988448,
    "n_ratings": 1199108
  },
  {
    "year": 2005,
    "avg_rating": 3.4321214000794846,
    "n_ratings": 1844381
  },
  {
    "year": 2006,
    "avg_rating": 3.4603671366324824,
    "n_ratings": 1207180
  },
  {
    "year": 2007,
    "avg_rating": 3.4642863030636075,
    "n_ratings": 1091850
  },
  {
    "year": 2008,
    "avg_rating": 3.5276055937354953,
    "n_ratings": 1202202
  },
  {
    "year": 2009,
    "avg_rating": 3.490106929746329,
    "n_ratings": 978867
  },
  {
    "year": 2010,
    "avg_rating": 3.5102754702741263,
    "n_ratings": 967255
  },
  {
    "year": 2011,
    "avg_rating": 3.536262258055468,
    "n_ratings": 819971
  },
  {
    "year": 2012,
    "avg_rating": 3.5869945676074524,
    "n_ratings": 779951
  },
  {
    "year": 2013,
    "avg_rating": 3.627331871145061,
    "n_ratings": 621443
  },
  {
    "year": 2014,
    "avg_rating": 3.6015719307905716,
    "n_ratings": 566628
  },
  {
    "year": 2015,
    "avg_rating": 3.578271012284416,
    "n_ratings": 1853975
  },
  {
    "year": 2016,
    "avg_rating": 3.5483674056408367,
    "n_ratings": 2005979
  },
  {
    "year": 2017,
    "avg_rating": 3.562181400277859,
    "n_ratings": 1899523
  },
  {
    "year": 2018,
    "avg_rating": 3.582863922517494,
    "n_ratings": 1455193
  },
  {
    "year": 2019,
    "avg_rating": 3.5938789892278264,
    "n_ratings": 1450218
  },
  {
    "year": 2020,
    "avg_rating": 3.6085078127303616,
    "n_ratings": 1763532
  },
  {
    "year": 2021,
    "avg_rating": 3.5968740486695823,
    "n_ratings": 1297525
  },
  {
    "year": 2022,
    "avg_rating": 3.517503070760174,
    "n_ratings": 953347
  },
  {
    "year": 2023,
    "avg_rating": 3.5749168183369355,
    "n_ratings": 562624
  }
]